magic_admin/__init__.py
magic_admin/config.py
magic_admin/error.py
magic_admin/http_client.py
magic_admin/magic.py
magic_admin/response.py
magic_admin/version.py
magic_admin/django/__init__.py
magic_admin/django/config.py
magic_admin/django/exceptions.py
magic_admin/django/utils.py
magic_admin/django/auth/__init__.py
magic_admin/django/auth/backends.py
magic_admin/django/auth/middleware.py
magic_admin/django/auth/models.py
magic_admin/resources/__init__.py
magic_admin/resources/base.py
magic_admin/resources/token.py
magic_admin/resources/user.py
magic_admin/utils/__init__.py
magic_admin/utils/did_token.py
magic_admin/utils/http.py
magic_admin/utils/logging.py
magic_admin/utils/time.py
django_magic_fortmatic-0.0.3.dist-info/LICENSE.txt
django_magic_fortmatic-0.0.3.dist-info/METADATA
django_magic_fortmatic-0.0.3.dist-info/WHEEL
django_magic_fortmatic-0.0.3.dist-info/top_level.txt
django_magic_fortmatic-0.0.3.dist-info/RECORD
