Metadata-Version: 2.1
Name: django-magic-fortmatic
Version: 0.0.3
Summary: Magic Python Library
Home-page: https://magic.link
Author: Magic
Author-email: support@magic.link
License: MIT
Project-URL: Website, https://github.com/voith/magic-admin-python
Keywords: magic python sdk
Platform: UNKNOWN
Classifier: Development Status :: 3 - Alpha
Classifier: Programming Language :: Python
Classifier: Programming Language :: Python :: 3.6
Classifier: Intended Audience :: Developers
Classifier: License :: OSI Approved :: MIT License
Classifier: Operating System :: OS Independent
Requires-Python: >=3.6
Requires-Dist: requests (==2.22.0)
Requires-Dist: web3 (==5.4.0)
Requires-Dist: Django (==2.2.1)
